tkcolorpicker/__init__.py
tkcolorpicker/__main__.py
tkcolorpicker/alphabar.py
tkcolorpicker/colorpicker.py
tkcolorpicker/colorsquare.py
tkcolorpicker/functions.py
tkcolorpicker/gradientbar.py
tkcolorpicker/limitvar.py
tkcolorpicker/spinbox.py
tkColorPicker2-1.0.dist-info/LICENSE.txt
tkColorPicker2-1.0.dist-info/METADATA
tkColorPicker2-1.0.dist-info/WHEEL
tkColorPicker2-1.0.dist-info/top_level.txt
tkColorPicker2-1.0.dist-info/RECORD
