Metadata-Version: 2.1
Name: tkColorPicker2
Version: 1.0
Summary: Color picker dialog for Tkinter forked from original
Author-email: Juliette Monsel <j_4321@protonmail.com>, Grigory Sharov <sharov.grigory@gmail.com>, Pablo Conesa <pconesa@cnb.csic.es>
License: GNU General Public License v3 (GPLv3)
Project-URL: Homepage, https://github.com/scipion-em/tkColorPicker
Project-URL: Repository, https://github.com/scipion-em/tkColorPicker
Project-URL: Issues, https://github.com/scipion-em/tkColorPicker/issues
Keywords: tkinter,color,colorchooser
Requires-Python: >=2.7
License-File: LICENSE.txt
Requires-Dist: Pillow
